<?xml version='1.0' encoding='UTF-8'?>
<imageMask imageWidth="1920" count="1" imageHeight="1080">
 <mask>
  <pt>1047.43,71.1429</pt>
  <pt>1036.29,78</pt>
  <pt>1032.86,80.5714</pt>
  <pt>1022.57,86.5714</pt>
  <pt>1016.57,91.7143</pt>
  <pt>988.286,113.143</pt>
  <pt>948,147.429</pt>
  <pt>929.143,163.714</pt>
  <pt>900,193.714</pt>
  <pt>881.143,217.714</pt>
  <pt>864.857,245.143</pt>
  <pt>848.571,272.571</pt>
  <pt>834,298.286</pt>
  <pt>826.286,320.571</pt>
  <pt>821.143,340.286</pt>
  <pt>816.857,356.571</pt>
  <pt>806.571,388.286</pt>
  <pt>803.143,408</pt>
  <pt>799.714,425.143</pt>
  <pt>798.857,440.571</pt>
  <pt>798.857,456</pt>
  <pt>798.857,469.714</pt>
  <pt>798.857,481.714</pt>
  <pt>799.714,495.429</pt>
  <pt>803.143,510</pt>
  <pt>808.286,524.571</pt>
  <pt>812.571,536.571</pt>
  <pt>815.143,550.286</pt>
  <pt>828,571.714</pt>
  <pt>837.429,583.714</pt>
  <pt>845.143,592.286</pt>
  <pt>857.143,607.714</pt>
  <pt>869.143,623.143</pt>
  <pt>883.714,647.143</pt>
  <pt>900,666.857</pt>
  <pt>923.143,700.286</pt>
  <pt>941.143,722.571</pt>
  <pt>963.429,749.143</pt>
  <pt>985.714,773.143</pt>
  <pt>1008.86,796.286</pt>
  <pt>1029.43,818.571</pt>
  <pt>1052.57,837.429</pt>
  <pt>1075.71,850.286</pt>
  <pt>1102.29,859.714</pt>
  <pt>1128,865.714</pt>
  <pt>1150.29,869.143</pt>
  <pt>1170.86,871.714</pt>
  <pt>1181.14,873.429</pt>
  <pt>1200.86,874.286</pt>
  <pt>1221.43,874.286</pt>
  <pt>1242,874.286</pt>
  <pt>1260.86,874.286</pt>
  <pt>1284,874.286</pt>
  <pt>1305.43,874.286</pt>
  <pt>1326,874.286</pt>
  <pt>1346.57,874.286</pt>
  <pt>1365.43,874.286</pt>
  <pt>1380.86,874.286</pt>
  <pt>1399.71,874.286</pt>
  <pt>1415.14,874.286</pt>
  <pt>1445.14,864</pt>
  <pt>1464.86,858</pt>
  <pt>1484.57,855.429</pt>
  <pt>1504.29,852.857</pt>
  <pt>1521.43,851.143</pt>
  <pt>1536.86,849.429</pt>
  <pt>1551.43,848.571</pt>
  <pt>1566,846</pt>
  <pt>1579.71,840.857</pt>
  <pt>1593.43,837.429</pt>
  <pt>1606.29,831.429</pt>
  <pt>1625.14,816</pt>
  <pt>1634.57,807.429</pt>
  <pt>1644,792.857</pt>
  <pt>1655.14,778.286</pt>
  <pt>1666.29,762.857</pt>
  <pt>1680,743.143</pt>
  <pt>1691.14,727.714</pt>
  <pt>1701.43,713.143</pt>
  <pt>1709.14,698.571</pt>
  <pt>1719.43,675.429</pt>
  <pt>1726.29,647.143</pt>
  <pt>1728,625.714</pt>
  <pt>1728.86,597.429</pt>
  <pt>1728.86,578.571</pt>
  <pt>1730.57,561.429</pt>
  <pt>1730.57,536.571</pt>
  <pt>1730.57,512.571</pt>
  <pt>1733.14,487.714</pt>
  <pt>1737.43,463.714</pt>
  <pt>1740,441.429</pt>
  <pt>1742.57,420.857</pt>
  <pt>1747.71,399.429</pt>
  <pt>1752,375.429</pt>
  <pt>1756.29,352.286</pt>
  <pt>1758.86,323.143</pt>
  <pt>1761.43,309.429</pt>
  <pt>1763.14,294.857</pt>
  <pt>1763.14,282.857</pt>
  <pt>1763.14,268.286</pt>
  <pt>1763.14,254.571</pt>
  <pt>1763.14,242.571</pt>
  <pt>1763.14,234</pt>
  <pt>1763.14,222.857</pt>
  <pt>1763.14,213.429</pt>
  <pt>1760.57,203.143</pt>
  <pt>1754.57,187.714</pt>
  <pt>1746.86,176.571</pt>
  <pt>1738.29,167.143</pt>
  <pt>1728.86,155.143</pt>
  <pt>1715.14,139.714</pt>
  <pt>1703.14,130.286</pt>
  <pt>1691.14,121.714</pt>
  <pt>1676.57,111.429</pt>
  <pt>1662.86,103.714</pt>
  <pt>1649.14,96.8571</pt>
  <pt>1636.29,90</pt>
  <pt>1622.57,81.4286</pt>
  <pt>1606.29,72</pt>
  <pt>1594.29,64.2857</pt>
  <pt>1583.14,56.5714</pt>
  <pt>1568.57,48.8571</pt>
  <pt>1552.29,42.8571</pt>
  <pt>1535.14,36.8571</pt>
  <pt>1520.57,30.8571</pt>
  <pt>1504.29,28.2857</pt>
  <pt>1490.57,24</pt>
  <pt>1475.14,18.8571</pt>
  <pt>1460.57,16.2857</pt>
  <pt>1446.86,11.1429</pt>
  <pt>1428.86,6</pt>
  <pt>1420.29,5.14286</pt>
  <pt>1411.71,4.28571</pt>
  <pt>1406.57,0.857143</pt>
  <pt>1402.29,0</pt>
  <pt>1102.29,0</pt>
  <pt>1070.57,20.5714</pt>
  <pt>1066.29,22.2857</pt>
  <pt>1056.86,29.1429</pt>
  <pt>1051.71,31.7143</pt>
  <pt>1050.86,33.4286</pt>
  <pt>1050.86,35.1429</pt>
  <pt>1050.86,36.8571</pt>
  <pt>1051.71,38.5714</pt>
  <pt>1055.14,41.1429</pt>
  <pt>1059.43,42.8571</pt>
  <pt>1060.29,43.7143</pt>
 </mask>
 <timeStamp>2020-08-04T19:43:58</timeStamp>
 <sysInfo>
  <hostName>MP4-TGI-084</hostName>
  <productName>Ubuntu 18.04.4 LTS</productName>
  <kernelVersion>5.4.0-42-generic</kernelVersion>
  <cpuArch>x86_64</cpuArch>
 </sysInfo>
</imageMask>
